{
  "version": "next",
  "tabs": [
    {
      "tab": "Documentation",
      "groups": [
        { "group": "Transactions & Fees", "pages": [] },
        { "group": "Messaging & Queries", "pages": [
          "docs/sdk/next/build/building-modules/messaging-and-queries"
        ]},
        { "group": "Integration", "groups": [
          { "group": "App Wiring & Runtime", "pages": [] },
          { "group": "Module Wiring", "pages": [] },
          { "group": "Upgrades & Migrations", "pages": [] },
          { "group": "Messaging Integration", "pages": [] },
          { "group": "Vote Extensions (End-to-End)", "pages": [] }
        ]},
        { "group": "Module Anatomy & Keepers", "pages": [] },
        { "group": "Runtime & ABCI", "pages": [
          "docs/sdk/next/build/abci/index"
        ]},
        { "group": "State & Store", "pages": [] },
        { "group": "Encoding & Protobuf", "pages": [] },
        { "group": "Testing & Simulation", "pages": [] },
        { "group": "Core Concepts", "pages": [
          "docs/sdk/next/index"
        ]},
        { "group": "Node Operations", "pages": [] },
        { "group": "Tooling", "pages": [] }
      ]
    },
    { "tab": "Module Reference", "groups": [] },
    { "tab": "API Reference", "pages": [] },
    { "tab": "Release Notes", "pages": [] }
  ]
}

